nanome_chemical_properties/ChemicalProperties.py
nanome_chemical_properties/ESOLCalculator.py
nanome_chemical_properties/RDKitHelper.py
nanome_chemical_properties/__init__.py
nanome_chemical_properties/icons/check.png
nanome_chemical_properties/icons/edit.png
nanome_chemical_properties/icons/frame.png
nanome_chemical_properties/icons/selection.png
nanome_chemical_properties/menus/MainMenu.py
nanome_chemical_properties/menus/SettingsMenu.py
nanome_chemical_properties/menus/SnapshotMenu.py
nanome_chemical_properties/menus/SnapshotsMenu.py
nanome_chemical_properties/menus/__init__.py
nanome_chemical_properties/menus/json/main.json
nanome_chemical_properties/menus/json/settings.json
nanome_chemical_properties/menus/json/snapshot.json
nanome_chemical_properties/menus/json/snapshots.json
nanome_chemical_properties-0.3.5.dist-info/LICENSE
nanome_chemical_properties-0.3.5.dist-info/METADATA
nanome_chemical_properties-0.3.5.dist-info/WHEEL
nanome_chemical_properties-0.3.5.dist-info/entry_points.txt
nanome_chemical_properties-0.3.5.dist-info/top_level.txt
nanome_chemical_properties-0.3.5.dist-info/RECORD
