Metadata-Version: 2.1
Name: nanome-chemical-properties
Version: 0.3.5
Summary: A Nanome plugin to display chemical properties for a complex using rdkit
Home-page: https://github.com/nanome-ai/plugin-chemical-properties
Author: Nanome
Author-email: hello@nanome.ai
License: MIT
Keywords: virtual-reality,chemistry,python,api,plugin
Platform: any
Classifier: Development Status :: 3 - Alpha
Classifier: Intended Audience :: Science/Research
Classifier: Topic :: Scientific/Engineering :: Chemistry
Classifier: License :: OSI Approved :: MIT License
Classifier: Programming Language :: Python :: 2.7
Classifier: Programming Language :: Python :: 3.5
Classifier: Programming Language :: Python :: 3.6
Classifier: Programming Language :: Python :: 3.7
Requires-Dist: nanome
Requires-Dist: cairosvg
